flask_hintful/__init__.py
flask_hintful/deserializer.py
flask_hintful/flask_hintful.py
flask_hintful/openapi.py
flask_hintful/serializer.py
flask_hintful/utils.py
flask_hintful/wrapper.py
flask_hintful-0.0.7.dist-info/LICENSE
flask_hintful-0.0.7.dist-info/METADATA
flask_hintful-0.0.7.dist-info/WHEEL
flask_hintful-0.0.7.dist-info/top_level.txt
flask_hintful-0.0.7.dist-info/RECORD
